[
    {
        "id":1,
        "title": "Web Development",
        "image" : "https://images.app.goo.gl/foT2UBhg6vbeeYPr9",
        "Description": "Lorem Ipsum is simply dummy text of the printing and typesetting industry. Lorem Ipsum has been the industry's standard dummy text ever since the 1500s, when an unknown printer took a galley of type and scrambled it to make a type specimen book."
},
{
    "id":1,
    "title": "Web Development",
    "image" : "https://images.app.goo.gl/foT2UBhg6vbeeYPr9",
    "Description": "Lorem Ipsum is simply dummy text of the printing and typesetting industry. Lorem Ipsum has been the industry's standard dummy text ever since the 1500s, when an unknown printer took a galley of type and scrambled it to make a type specimen book."
}
]